blinklinmult/__init__.py
blinklinmult/demo/__init__.py
blinklinmult/demo/talkingface_feature_extraction.py
blinklinmult/demo/talkingface_inference.py
blinklinmult/models/BlinkLinMulT.py
blinklinmult/models/__init__.py
blinklinmult/models/backbone.py
blinklinmult/models/clip_wrapper.py
blinklinmult/models/efficientnetv2.py
blinklinmult/models/gru.py
blinklinmult/preprocess/__init__.py
blinklinmult/preprocess/cew.py
blinklinmult/preprocess/eyeblink8.py
blinklinmult/preprocess/mrl.py
blinklinmult/preprocess/reader.py
blinklinmult/preprocess/rn.py
blinklinmult/preprocess/rtgene.py
blinklinmult/preprocess/talkingface.py
blinklinmult/preprocess/zju.py
blinklinmult-1.0.2.dist-info/METADATA
blinklinmult-1.0.2.dist-info/WHEEL
blinklinmult-1.0.2.dist-info/licenses/LICENSE
blinklinmult-1.0.2.dist-info/RECORD
