Metadata-Version: 2.4
Name: blinklinmult
Version: 1.0.2
Summary: BlinkLinMulT: Transformer-based Eye Blink Detection.
Project-URL: Documentation, https://github.com/fodorad/blinklinmult#readme
Project-URL: Issues, https://github.com/fodorad/blinklinmult/issues
Project-URL: Source, https://github.com/fodorad/blinklinmult
Author-email: fodorad <foauaai@inf.elte.hu>
License-Expression: MIT
License-File: LICENSE
Keywords: blink,blink presence detection,eye state recognition,linear-complexity attention,multimodal,transformer
Classifier: License :: OSI Approved :: MIT License
Classifier: Operating System :: OS Independent
Classifier: Programming Language :: Python :: 3
Requires-Python: >=3.11
Requires-Dist: bbox-visualizer
Requires-Dist: exordium[tddfa]
Requires-Dist: linmult==1.1.0
Requires-Dist: matplotlib
Requires-Dist: moviepy
Requires-Dist: opencv-python
Requires-Dist: pyyaml
Requires-Dist: scipy
Requires-Dist: toml
Requires-Dist: torch
Requires-Dist: torchvision
Requires-Dist: tqdm
Provides-Extra: all
Requires-Dist: clip; extra == 'all'
Requires-Dist: pytorch-lightning==1.8.4; extra == 'all'
Requires-Dist: torchsampler; extra == 'all'
Provides-Extra: inference
Requires-Dist: exordium[tddfa]; extra == 'inference'
Provides-Extra: train
Requires-Dist: pytorch-lightning==1.8.4; extra == 'train'
Requires-Dist: torchsampler; extra == 'train'
